bobByDew/__init__.py
bobByDew/bobByDew.py
bobByDew-1.0.data/data/bin/bobByDew.py
bobByDew-1.0.dist-info/LICENSE.txt
bobByDew-1.0.dist-info/METADATA
bobByDew-1.0.dist-info/WHEEL
bobByDew-1.0.dist-info/entry_points.txt
bobByDew-1.0.dist-info/top_level.txt
bobByDew-1.0.dist-info/RECORD
