Metadata-Version: 2.1
Name: bobByDew
Version: 1.0
Summary: This Python package provides a real-time visualization of cryptocurrency order books from the Binance exchange. Utilizing asynchronous programming and WebSockets, it streams market depth data for BTC/USDT and calculates key trading metrics. The package features a terminal-based user interface created with the curses library to display bids, asks, spread, weighted averages, total volume, and order flow imbalance, updating dynamically to reflect live market conditions.
Home-page: https://github.com/yourusername/your_package_name
Author: Mr Dew
Author-email: james@meeteden.dev
License-File: LICENSE.txt
Requires-Dist: websockets
